dna_utils/__init__.py
dna_utils/__version__.py
dna_utils/dna_utils.py
dna_utils/mapper.py
dnautils-0.1.0.dist-info/WHEEL
dnautils-0.1.0.dist-info/METADATA
dnautils-0.1.0.dist-info/RECORD
