Metadata-Version: 2.1
Name: dnautils
Version: 0.1.0
Summary: 
Author: Benoitdw
Author-email: bw@oncodna.com
Requires-Python: >=3.11,<4.0
Classifier: Programming Language :: Python :: 3
Classifier: Programming Language :: Python :: 3.11
Requires-Dist: pyfaidx (>=0.7.2.1,<0.8.0.0)
Requires-Dist: pytest (>=7.2.1,<8.0.0)
